ipympl/__init__.py
ipympl/_version.py
ipympl/backend_nbagg.py
ipympl/labextension/package.json
ipympl/labextension/static/108.f3cb11fd5eb2ca234df3.js
ipympl/labextension/static/480.65349f032615df3e4551.js
ipympl/labextension/static/486.7f21edf44990ca646366.js
ipympl/labextension/static/486.7f21edf44990ca646366.js.LICENSE.txt
ipympl/labextension/static/686.0cd480be1ec32cebbf7f.js
ipympl/labextension/static/remoteEntry.2245c790a510bf1865ea.js
ipympl/labextension/static/style.js
ipympl/labextension/static/third-party-licenses.json
ipympl/nbextension/extension.js
ipympl/nbextension/index.js
ipympl/nbextension/index.js.LICENSE.txt
ipympl/nbextension/index.js.map
ipympl-0.9.3.data/data/etc/jupyter/nbconfig/notebook.d/jupyter-matplotlib.json
ipympl-0.9.3.data/data/share/jupyter/labextensions/jupyter-matplotlib/package.json
ipympl-0.9.3.data/data/share/jupyter/labextensions/jupyter-matplotlib/static/108.f3cb11fd5eb2ca234df3.js
ipympl-0.9.3.data/data/share/jupyter/labextensions/jupyter-matplotlib/static/480.65349f032615df3e4551.js
ipympl-0.9.3.data/data/share/jupyter/labextensions/jupyter-matplotlib/static/486.7f21edf44990ca646366.js
ipympl-0.9.3.data/data/share/jupyter/labextensions/jupyter-matplotlib/static/486.7f21edf44990ca646366.js.LICENSE.txt
ipympl-0.9.3.data/data/share/jupyter/labextensions/jupyter-matplotlib/static/686.0cd480be1ec32cebbf7f.js
ipympl-0.9.3.data/data/share/jupyter/labextensions/jupyter-matplotlib/static/remoteEntry.2245c790a510bf1865ea.js
ipympl-0.9.3.data/data/share/jupyter/labextensions/jupyter-matplotlib/static/style.js
ipympl-0.9.3.data/data/share/jupyter/labextensions/jupyter-matplotlib/static/third-party-licenses.json
ipympl-0.9.3.data/data/share/jupyter/nbextensions/jupyter-matplotlib/extension.js
ipympl-0.9.3.data/data/share/jupyter/nbextensions/jupyter-matplotlib/index.js
ipympl-0.9.3.data/data/share/jupyter/nbextensions/jupyter-matplotlib/index.js.LICENSE.txt
ipympl-0.9.3.data/data/share/jupyter/nbextensions/jupyter-matplotlib/index.js.map
ipympl-0.9.3.dist-info/LICENSE
ipympl-0.9.3.dist-info/METADATA
ipympl-0.9.3.dist-info/WHEEL
ipympl-0.9.3.dist-info/top_level.txt
ipympl-0.9.3.dist-info/RECORD
