Metadata-Version: 2.1
Name: ipympl
Version: 0.9.3
Summary: Matplotlib Jupyter Extension
Home-page: http://matplotlib.org
Author: Matplotlib Development Team
Author-email: matplotlib-users@python.org
License: BSD License
Keywords: ipython,jupyter,widgets,graphics
Classifier: Development Status :: 4 - Beta
Classifier: Framework :: IPython
Classifier: Intended Audience :: Developers
Classifier: Intended Audience :: Science/Research
Classifier: Topic :: Multimedia :: Graphics
Classifier: Programming Language :: Python :: 2
Classifier: Programming Language :: Python :: 3.5
Classifier: Programming Language :: Python :: 3.6
Classifier: Programming Language :: Python :: 3.7
Classifier: Programming Language :: Python :: 3.8
Classifier: Programming Language :: Python :: 3.9
Provides-Extra: docs
License-File: LICENSE
